apache_airflow_microsoft_fabric_plugin/__init__.py
apache_airflow_microsoft_fabric_plugin/hooks/__init__.py
apache_airflow_microsoft_fabric_plugin/hooks/fabric.py
apache_airflow_microsoft_fabric_plugin/operators/__init__.py
apache_airflow_microsoft_fabric_plugin/operators/fabric.py
apache_airflow_microsoft_fabric_plugin/triggers/__init__.py
apache_airflow_microsoft_fabric_plugin/triggers/fabric.py
apache_airflow_microsoft_fabric_plugin_custom-1.0.6.dist-info/LICENSE
apache_airflow_microsoft_fabric_plugin_custom-1.0.6.dist-info/METADATA
apache_airflow_microsoft_fabric_plugin_custom-1.0.6.dist-info/WHEEL
apache_airflow_microsoft_fabric_plugin_custom-1.0.6.dist-info/top_level.txt
apache_airflow_microsoft_fabric_plugin_custom-1.0.6.dist-info/RECORD
