Metadata-Version: 2.1
Name: apache_airflow_microsoft_fabric_plugin_custom
Version: 1.0.6
Summary: A plugin for Apache Airflow to interact with Microsoft Fabric items with small custom change
Author-email: Ambika Garg <ambikagarg1101@gmail.com>, Domagoj Gusic <dgusic94@gmail.com>
Project-URL: Homepage, https://github.com/ambika-garg/apache-airflow-microsoft-fabric-plugin-custom.git
Classifier: Programming Language :: Python :: 3
Classifier: Development Status :: 3 - Alpha
Classifier: Environment :: Plugins
Classifier: Intended Audience :: Developers
Classifier: Topic :: Software Development :: Libraries :: Python Modules
Requires-Python: >=3.8
License-File: LICENSE
